perspectra/__init__.py
perspectra/__main__.py
perspectra/approximate_polygon.py
perspectra/binarize.py
perspectra/cli.py
perspectra/file_utils.py
perspectra/multipass_cleaner.py
perspectra/noise_generator.py
perspectra/splitter.py
perspectra/transformer.py
perspectra-0.2.1.dist-info/METADATA
perspectra-0.2.1.dist-info/WHEEL
perspectra-0.2.1.dist-info/entry_points.txt
perspectra-0.2.1.dist-info/RECORD
