Metadata-Version: 2.3
Name: perspectra
Version: 0.2.1
Summary: Automatically extract and perspectively correct documents in images
Project-URL: Homepage, http://github.com/ad-si/Perspectra
Author-email: Adrian Sieber <mail@adriansieber.com>
License: ISC
Keywords: document scanner,perspective transformation
Classifier: Development Status :: 3 - Alpha
Classifier: Environment :: Console
Classifier: Intended Audience :: End Users/Desktop
Classifier: Natural Language :: English
Classifier: Operating System :: OS Independent
Classifier: Programming Language :: Python :: 3
Classifier: Topic :: Scientific/Engineering :: Image Recognition
Requires-Python: >=3.12
Requires-Dist: imageio>=2.36.0
Requires-Dist: matplotlib>=3.9.2
Requires-Dist: numpy>=2.1.3
Requires-Dist: packaging>=24.2
Requires-Dist: pandas>=2.2.3
Requires-Dist: plotly>=5.24.1
Requires-Dist: scikit-image>=0.24.0
